si_prefix_parser/__init__.py
si_prefix_parser/si_prefix_parser.py
si_prefix_parser-0.1.0.dist-info/METADATA
si_prefix_parser-0.1.0.dist-info/WHEEL
si_prefix_parser-0.1.0.dist-info/top_level.txt
si_prefix_parser-0.1.0.dist-info/RECORD
