Metadata-Version: 2.1
Name: si-prefix-parser
Version: 0.1.0
Summary: A small utility to turn strings like '14.5M' into 14500000.0
Home-page: UNKNOWN
Author: Adrian Campos
Author-email: adrian@g4tv.com
License: UNKNOWN
Platform: UNKNOWN
Classifier: Programming Language :: Python :: 3
Classifier: Operating System :: OS Independent
Requires-Python: >=3.6
